[
    {
        "img": "",
        "name": "Mr.Jhon",
        "review":"Customers want someone just like them, even when it comes to picking a company."
    },
    {
        "img": "",
        "name": "Mr. Akbar Ali",
        "review":"If the end result is customer satisfaction, your business will thrive. If the end result is customer loyalty, your business will bloom."
    },
    {
        "img": "",
        "name": "Jhon Karir",
        "review":"A customer talking about their experience with you is worth ten times that which you write or say about yourself."
    },
    {
        "img": "",
        "name": "Young Born",
        "review":"Your marketing plan is not as important as how you plan to invest in the happiness of your customers."
    },
    {
        "img": "",
        "name": "Thomas Mir",
        "review":"Your customer service opens up unique opportunities to offer an excellent customer experience."
    },
    {
        "img": "",
        "name": "Kori Andershon",
        "review":"Great customer service alone can make us buy something we know we do not need."
    }
]